xiangqi/__init__.py
xiangqi/board.py
xiangqi/constants.py
xiangqi/env.py
xiangqi/helper.py
xiangqi/piece.py
xiangqi/force/__init__.py
xiangqi/force/bing.py
xiangqi/force/ju.py
xiangqi/force/ma.py
xiangqi/force/pao.py
xiangqi/force/shi.py
xiangqi/force/shuai.py
xiangqi/force/xiang.py
xiangqi-1.0.5.dist-info/LICENSE
xiangqi-1.0.5.dist-info/METADATA
xiangqi-1.0.5.dist-info/WHEEL
xiangqi-1.0.5.dist-info/top_level.txt
xiangqi-1.0.5.dist-info/RECORD
