Metadata-Version: 2.1
Name: xiangqi
Version: 1.0.5
Summary: Chinese Chess Environment for Reinforcement Learning
Home-page: https://github.com/splendor-kill/xiangqi
Author: Splendor
Author-email: splendor.kill@gmail.com
Project-URL: Bug Tracker, https://github.com/splendor-kill/xiangqi/issues
Keywords: Zhong Guo Xiang Qi,Chinese chess,OpenAI Gym-compatible,中国象棋,强化学习环境
Classifier: Programming Language :: Python :: 3
Classifier: License :: OSI Approved :: MIT License
Classifier: Operating System :: OS Independent
Requires-Python: >=3.6
License-File: LICENSE
